gom/__init__.py
gom/main.py
gom/utils.py
gom-0.3.2.dist-info/METADATA
gom-0.3.2.dist-info/WHEEL
gom-0.3.2.dist-info/entry_points.txt
gom-0.3.2.dist-info/licenses/LICENSE
gom-0.3.2.dist-info/RECORD
