Metadata-Version: 2.4
Name: gom
Version: 0.3.2
Summary: Live GPU utilization monitor, inspired by nvidia-smi. Shows per-container GPU usage as well as total GPU usage.
License-File: LICENSE
Author: Ben Gubler
Author-email: nebrelbug@gmail.com
Requires-Python: >=3.8,<4.0
Classifier: Programming Language :: Python :: 3
Classifier: Programming Language :: Python :: 3.8
Classifier: Programming Language :: Python :: 3.9
Classifier: Programming Language :: Python :: 3.10
Classifier: Programming Language :: Python :: 3.11
Classifier: Programming Language :: Python :: 3.12
Classifier: Programming Language :: Python :: 3.13
Classifier: Programming Language :: Python :: 3.14
Requires-Dist: click (>=8.0.0,<9.0.0)
Requires-Dist: docker (>=7.1.0,<8.0.0)
Requires-Dist: pynvml (>=11.0.0,<12.0.0)
Requires-Dist: tabulate (>=0.9.0,<0.10.0)
